g42cloudsdkcbr/__init__.py
g42cloudsdkcbr/v1/__init__.py
g42cloudsdkcbr/v1/cbr_async_client.py
g42cloudsdkcbr/v1/cbr_client.py
g42cloudsdkcbr/v1/model/__init__.py
g42cloudsdkcbr/v1/model/add_member_request.py
g42cloudsdkcbr/v1/model/add_member_response.py
g42cloudsdkcbr/v1/model/add_members_req.py
g42cloudsdkcbr/v1/model/add_vault_resource_request.py
g42cloudsdkcbr/v1/model/add_vault_resource_response.py
g42cloudsdkcbr/v1/model/associate_vault_policy_request.py
g42cloudsdkcbr/v1/model/associate_vault_policy_response.py
g42cloudsdkcbr/v1/model/backup_extend_info.py
g42cloudsdkcbr/v1/model/backup_resp.py
g42cloudsdkcbr/v1/model/backup_restore.py
g42cloudsdkcbr/v1/model/backup_restore_req.py
g42cloudsdkcbr/v1/model/backup_restore_server_mapping.py
g42cloudsdkcbr/v1/model/batch_create_and_delete_vault_tags_request.py
g42cloudsdkcbr/v1/model/batch_create_and_delete_vault_tags_response.py
g42cloudsdkcbr/v1/model/billbing_create_extra_info.py
g42cloudsdkcbr/v1/model/billing.py
g42cloudsdkcbr/v1/model/billing_create.py
g42cloudsdkcbr/v1/model/billing_update.py
g42cloudsdkcbr/v1/model/bind_rules_tags.py
g42cloudsdkcbr/v1/model/bulk_create_and_delete_vault_tags_req.py
g42cloudsdkcbr/v1/model/cbc_order_result.py
g42cloudsdkcbr/v1/model/checkpoint_create.py
g42cloudsdkcbr/v1/model/checkpoint_create_skipped_resource.py
g42cloudsdkcbr/v1/model/checkpoint_extra_info_resp.py
g42cloudsdkcbr/v1/model/checkpoint_param.py
g42cloudsdkcbr/v1/model/checkpoint_plan_create.py
g42cloudsdkcbr/v1/model/checkpoint_resource_resp.py
g42cloudsdkcbr/v1/model/create_checkpoint_request.py
g42cloudsdkcbr/v1/model/create_checkpoint_response.py
g42cloudsdkcbr/v1/model/create_policy_request.py
g42cloudsdkcbr/v1/model/create_policy_response.py
g42cloudsdkcbr/v1/model/create_vault_request.py
g42cloudsdkcbr/v1/model/create_vault_response.py
g42cloudsdkcbr/v1/model/create_vault_tags_request.py
g42cloudsdkcbr/v1/model/create_vault_tags_response.py
g42cloudsdkcbr/v1/model/delete_backup_request.py
g42cloudsdkcbr-0.0.10b0.dist-info/LICENSE
g42cloudsdkcbr-0.0.10b0.dist-info/METADATA
g42cloudsdkcbr-0.0.10b0.dist-info/WHEEL
g42cloudsdkcbr-0.0.10b0.dist-info/top_level.txt
g42cloudsdkcbr-0.0.10b0.dist-info/RECORD
